simpleemoji/__init__.py
simpleemoji-0.1.0.dist-info/METADATA
simpleemoji-0.1.0.dist-info/WHEEL
simpleemoji-0.1.0.dist-info/top_level.txt
simpleemoji-0.1.0.dist-info/RECORD
