Metadata-Version: 2.4
Name: simpleemoji
Version: 0.1.0
Summary: A tiny package to get some simple emojis in Python
Author: Dextro
Author-email: levovarma@gmail.com
Classifier: Programming Language :: Python :: 3
Classifier: License :: OSI Approved :: MIT License
Classifier: Operating System :: OS Independent
Requires-Python: >=3.6
Dynamic: author
Dynamic: author-email
Dynamic: classifier
Dynamic: description
Dynamic: description-content-type
Dynamic: requires-python
Dynamic: summary
